{
  "repair_end": "2018-12-08 04:35:57.182405", 
  "repair_begin": "2018-12-08 04:35:50.138912", 
  "patches": [
    {
      "PATCH_DIFF_ORIG": "\\/var\\/lib\\/oar\\/.batch_job_bashrc: line 5: \\/home\\/tdurieux\\/.bashrc: No such file or directory\\n--- introclassJava\\/median_6e464f2b_003.java\\n+++ introclassJava\\/median_6e464f2b_003.java\\n@@ -66,7 +66,7 @@\\n \\t\\tif ((((a.value) > (b.value)) && ((a.value) < (c.value))) || \\n \\t\\t(((a.value) < (b.value)) && ((a.value) > (c.value)))) {\\n \\t\\t\\toutput += java.lang.String.format(\\\"%d is the median\\\\n\\\", a.value);\\n-\\t\\t}else \\t\\t\\tif ((((b.value) > (a.value)) && ((b.value) < (c.value))) || \\n+\\t\\t}else \\t\\t\\tif ((((b.value) >= (a.value)) && ((b.value) < (c.value))) || \\n \\t\\t\\t(((b.value) < (a.value)) && ((b.value) > (c.value)))) {\\n \\t\\t\\t\\toutput += java.lang.String.format(\\\"%d is the median\\\\n\\\", b.value);\\n \\t\\t\\t}else {\\n\\n", 
      "patchhunks": [
        {
          "MODIFIED_FILE_PATH": "\\/tmp\\/jMutRepair_IntroClassJava_median_6e464f2b5ba1d5ad3d4fc366e7d7712b424aabd8b41ca36257115a16416d202feb27397a413d04944c9ac76976fa8ff8ae646144855e08791ebf9593d1caaaca_003\\/.\\/output_astor\\/AstorMain-median-6e464f2b5ba1d5ad3d4fc366e7d7712b424aabd8b41ca36257115a16416d202feb27397a413d04944c9ac76976fa8ff8ae646144855e08791ebf9593d1caaaca_003\\/\\/src\\/\\/variant-5_f\\/introclassJava\\/median_6e464f2b_003.java", 
          "ORIGINAL_CODE": "(((b.value) > (a.value)) && ((b.value) < (c.value))) || \\n(((b.value) < (a.value)) && ((b.value) > (c.value)))", 
          "PATCH_HUNK_CODE": "((\\n\\n\\n\\n\\n\\n\\n\\n\\n\\n\\n\\n\\n\\n\\n\\n\\n\\n\\n\\n\\n\\n\\n\\n\\n\\n\\n\\n\\n\\n\\n\\n\\n\\n\\n\\n\\n\\n\\n\\n\\n\\n\\n\\n\\n\\n\\n\\n\\n\\n\\n\\n\\n\\n\\n\\n\\n\\n\\n\\n\\n\\n\\n\\n\\n\\n\\n\\n(b.value) >= (a.value)) && ((b.value) < (c.value))) || \\n(((b.value) < (a.value)) && ((b.value) > (c.value)))", 
          "LOCATION": "introclassJava.median_6e464f2b_003", 
          "BUGGY_CODE_TYPE": "CtBinaryOperatorImpl|CtIfImpl", 
          "OPERATOR": "IfExpresionMutOp", 
          "PATH": "\\/tmp\\/jMutRepair_IntroClassJava_median_6e464f2b5ba1d5ad3d4fc366e7d7712b424aabd8b41ca36257115a16416d202feb27397a413d04944c9ac76976fa8ff8ae646144855e08791ebf9593d1caaaca_003\\/output_astor\\/AstorMain-median-6e464f2b5ba1d5ad3d4fc366e7d7712b424aabd8b41ca36257115a16416d202feb27397a413d04944c9ac76976fa8ff8ae646144855e08791ebf9593d1caaaca_003\\/src\\/default\\/introclassJava\\/median_6e464f2b_003.java", 
          "LINE": "69", 
          "MP_RANKING": "0", 
          "SUSPICIOUNESS": "0.302", 
          "PATCH_HUNK_TYPE": "CtBinaryOperatorImpl|CtIfImpl"
        }
      ], 
      "GENERATION": "1", 
      "VARIANT_ID": "5", 
      "TIME": "1", 
      "VALIDATION": "|true|0|13|[]|", 
      "FOLDER_SOLUTION_CODE": "\\/tmp\\/jMutRepair_IntroClassJava_median_6e464f2b5ba1d5ad3d4fc366e7d7712b424aabd8b41ca36257115a16416d202feb27397a413d04944c9ac76976fa8ff8ae646144855e08791ebf9593d1caaaca_003\\/.\\/output_astor\\/AstorMain-median-6e464f2b5ba1d5ad3d4fc366e7d7712b424aabd8b41ca36257115a16416d202feb27397a413d04944c9ac76976fa8ff8ae646144855e08791ebf9593d1caaaca_003\\/\\/bin\\/\\/variant-5"
    }
  ]
}