{
  "repair_end": "2019-01-03 04:06:35.042512", 
  "repair_begin": "2019-01-03 04:05:26.375907", 
  "patches": [
    {
      "PATCH_DIFF_ORIG": "\\/var\\/lib\\/oar\\/.batch_job_bashrc: line 5: \\/home\\/tdurieux\\/.bashrc: No such file or directory\\n--- \\/tmp\\/Cardumen_Bug_dot_jar_Commons-Math_f6dd42b4\\/src\\/main\\/java\\/org\\/apache\\/commons\\/math\\/analysis\\/solvers\\/BrentSolverjava\\n+++ \\/tmp\\/Cardumen_Bug_dot_jar_Commons-Math_f6dd42b4\\/src\\/main\\/java\\/org\\/apache\\/commons\\/math\\/analysis\\/solvers\\/BrentSolverjava\\n@@ -129,7 +129,7 @@\\n \\t\\t}\\n \\n \\n-\\t\\treturn solve(f, min, yMin, max, yMax, initial, yInitial);\\n+\\t\\treturn solve(f, max, max);\\n \\n \\t}\\n \\n\\n", 
      "patchhunks": [
        {
          "MODIFIED_FILE_PATH": "\\/tmp\\/Cardumen_Bug_dot_jar_Commons-Math_f6dd42b4\\/.\\/output_astor\\/AstorMain-Commons-Math-f6dd42b4\\/\\/src\\/\\/variant-314\\/org\\/apache\\/commons\\/math\\/analysis\\/solvers\\/BrentSolver.java", 
          "ORIGINAL_CODE": "solve(f, min, yMin, max, yMax, initial, yInitial)", 
          "INGREDIENT_SCOPE": "-", 
          "PATCH_HUNK_CODE": "solve(f, max, max)", 
          "INGREDIENT_PARENT": "solve(_UnivariateRealFunction_0, _double_1, _double_2)", 
          "LOCATION": "org.apache.commons.math.analysis.solvers.BrentSolver", 
          "BUGGY_CODE_TYPE": "CtInvocationImpl|CtReturnImpl", 
          "OPERATOR": "ExpressionReplaceOperator", 
          "PATH": "\\/tmp\\/Cardumen_Bug_dot_jar_Commons-Math_f6dd42b4\\/src\\/main\\/java\\/org\\/apache\\/commons\\/math\\/analysis\\/solvers\\/BrentSolver.java", 
          "LINE": "132", 
          "MP_RANKING": "0", 
          "SUSPICIOUNESS": "1", 
          "PATCH_HUNK_TYPE": "CtInvocationImpl|CtReturnImpl"
        }
      ], 
      "GENERATION": "157", 
      "VARIANT_ID": "314", 
      "TIME": "39", 
      "VALIDATION": "|true|0|2140|[]|", 
      "FOLDER_SOLUTION_CODE": "\\/tmp\\/Cardumen_Bug_dot_jar_Commons-Math_f6dd42b4\\/.\\/output_astor\\/AstorMain-Commons-Math-f6dd42b4\\/\\/bin\\/\\/variant-314"
    }
  ]
}