{
  "repair_end": "2018-11-28 15:44:24.627507", 
  "repair_begin": "2018-11-28 15:36:16.154801", 
  "patches": [
    {
      "edits": [
        {
          "path": "src/main/java/introclassJava/smallest_3b2376ab_007.java", 
          "line": 75, 
          "faulty": "if (n4.value < n3.value) {\n  small.value=n4.value;\n}\n else if (n4.value < n1.value) {\n  small.value=n4.value;\n}", 
          "type": "Replace", 
          "seed": "if (n4.value < n1.value) {\n  small.value=n4.value;\n}"
        }, 
        {
          "path": "src/main/java/introclassJava/smallest_3b2376ab_007.java", 
          "line": 76, 
          "faulty": "small.value=n4.value;", 
          "type": "Delete", 
          "seed": "if (n4.value < n1.value) {\n  small.value=n4.value;\n}"
        }, 
        {
          "path": "src/main/java/introclassJava/smallest_3b2376ab_007.java", 
          "line": 82, 
          "faulty": "return;", 
          "type": "Delete", 
          "seed": "output+=(String.format(\"Please enter 4 numbers separated by spaces > \"));"
        }
      ]
    }, 
    {
      "edits": [
        {
          "path": "src/main/java/introclassJava/smallest_3b2376ab_007.java", 
          "line": 65, 
          "faulty": "n2.value=scanner.nextInt();", 
          "type": "InsertBefore", 
          "seed": "if (n4.value < n1.value) {\n  small.value=n4.value;\n}"
        }, 
        {
          "path": "src/main/java/introclassJava/smallest_3b2376ab_007.java", 
          "line": 76, 
          "faulty": "small.value=n4.value;", 
          "type": "Replace", 
          "seed": "if (n4.value < n1.value) {\n  small.value=n4.value;\n}"
        }, 
        {
          "path": "src/main/java/introclassJava/smallest_3b2376ab_007.java", 
          "line": 82, 
          "faulty": ";", 
          "type": "InsertBefore", 
          "seed": "small.value=n1.value;"
        }
      ]
    }, 
    {
      "edits": [
        {
          "path": "src/main/java/introclassJava/smallest_3b2376ab_007.java", 
          "line": 76, 
          "faulty": "small.value=n4.value;", 
          "type": "Replace", 
          "seed": "if (n4.value < n1.value) {\n  small.value=n4.value;\n}"
        }, 
        {
          "path": "src/main/java/introclassJava/smallest_3b2376ab_007.java", 
          "line": 82, 
          "faulty": "return;", 
          "type": "Replace", 
          "seed": "small.value=n4.value;"
        }
      ]
    }, 
    {
      "edits": [
        {
          "path": "src/main/java/introclassJava/smallest_3b2376ab_007.java", 
          "line": 76, 
          "faulty": "small.value=n4.value;", 
          "type": "Replace", 
          "seed": "if (n4.value < n1.value) {\n  small.value=n4.value;\n}"
        }, 
        {
          "path": "src/main/java/introclassJava/smallest_3b2376ab_007.java", 
          "line": 82, 
          "faulty": ";", 
          "type": "InsertBefore", 
          "seed": "small.value=n3.value;"
        }
      ]
    }, 
    {
      "edits": [
        {
          "path": "src/main/java/introclassJava/smallest_3b2376ab_007.java", 
          "line": 72, 
          "faulty": "if (n3.value < n2.value) {\n  small.value=n3.value;\n}", 
          "type": "Delete", 
          "seed": "small.value=n2.value;"
        }, 
        {
          "path": "src/main/java/introclassJava/smallest_3b2376ab_007.java", 
          "line": 76, 
          "faulty": "small.value=n4.value;", 
          "type": "Replace", 
          "seed": "if (n4.value < n1.value) {\n  small.value=n4.value;\n}"
        }
      ]
    }, 
    {
      "edits": [
        {
          "path": "src/main/java/introclassJava/smallest_3b2376ab_007.java", 
          "line": 75, 
          "faulty": "if (n4.value < n3.value) {\n  small.value=n4.value;\n}\n else if (n4.value < n1.value) {\n  small.value=n4.value;\n}", 
          "type": "InsertBefore", 
          "seed": "if (n3.value < n2.value) {\n  small.value=n3.value;\n}"
        }, 
        {
          "path": "src/main/java/introclassJava/smallest_3b2376ab_007.java", 
          "line": 76, 
          "faulty": "small.value=n4.value;", 
          "type": "Replace", 
          "seed": "if (n4.value < n1.value) {\n  small.value=n4.value;\n}"
        }, 
        {
          "path": "src/main/java/introclassJava/smallest_3b2376ab_007.java", 
          "line": 82, 
          "faulty": "return;", 
          "type": "Delete", 
          "seed": "small.value=n4.value;"
        }
      ]
    }, 
    {
      "edits": [
        {
          "path": "src/main/java/introclassJava/smallest_3b2376ab_007.java", 
          "line": 76, 
          "faulty": "small.value=n4.value;", 
          "type": "Replace", 
          "seed": "if (n4.value < n1.value) {\n  small.value=n4.value;\n}"
        }, 
        {
          "path": "src/main/java/introclassJava/smallest_3b2376ab_007.java", 
          "line": 82, 
          "faulty": ";", 
          "type": "InsertBefore", 
          "seed": "output+=(String.format(\"Please enter 4 numbers separated by spaces > \"));"
        }
      ]
    }, 
    {
      "edits": [
        {
          "path": "src/main/java/introclassJava/smallest_3b2376ab_007.java", 
          "line": 62, 
          "faulty": "output+=(String.format(\"Please enter 4 numbers separated by spaces > \"));", 
          "type": "InsertBefore", 
          "seed": "if (n3.value < n2.value) {\n  small.value=n3.value;\n}"
        }, 
        {
          "path": "src/main/java/introclassJava/smallest_3b2376ab_007.java", 
          "line": 76, 
          "faulty": "small.value=n4.value;", 
          "type": "Replace", 
          "seed": "if (n4.value < n1.value) {\n  small.value=n4.value;\n}"
        }
      ]
    }, 
    {
      "edits": [
        {
          "path": "src/main/java/introclassJava/smallest_3b2376ab_007.java", 
          "line": 75, 
          "faulty": "if (n4.value < n3.value) {\n  small.value=n4.value;\n}\n else if (n4.value < n1.value) {\n  small.value=n4.value;\n}", 
          "type": "Replace", 
          "seed": "if (n4.value < n1.value) {\n  small.value=n4.value;\n}"
        }, 
        {
          "path": "src/main/java/introclassJava/smallest_3b2376ab_007.java", 
          "line": 76, 
          "faulty": "small.value=n4.value;", 
          "type": "Replace", 
          "seed": "if (n4.value < n1.value) {\n  small.value=n4.value;\n}"
        }, 
        {
          "path": "src/main/java/introclassJava/smallest_3b2376ab_007.java", 
          "line": 82, 
          "faulty": "return;", 
          "type": "Delete", 
          "seed": "output+=(String.format(\"Please enter 4 numbers separated by spaces > \"));"
        }
      ]
    }, 
    {
      "edits": [
        {
          "path": "src/main/java/introclassJava/smallest_3b2376ab_007.java", 
          "line": 68, 
          "faulty": "small.value=n1.value;", 
          "type": "InsertBefore", 
          "seed": "if (n4.value < n1.value) {\n  small.value=n4.value;\n}"
        }, 
        {
          "path": "src/main/java/introclassJava/smallest_3b2376ab_007.java", 
          "line": 76, 
          "faulty": "small.value=n4.value;", 
          "type": "Replace", 
          "seed": "if (n4.value < n1.value) {\n  small.value=n4.value;\n}"
        }, 
        {
          "path": "src/main/java/introclassJava/smallest_3b2376ab_007.java", 
          "line": 82, 
          "faulty": ";", 
          "type": "InsertBefore", 
          "seed": "output+=(String.format(\"Please enter 4 numbers separated by spaces > \"));"
        }
      ]
    }, 
    {
      "edits": [
        {
          "path": "src/main/java/introclassJava/smallest_3b2376ab_007.java", 
          "line": 65, 
          "faulty": "n2.value=scanner.nextInt();", 
          "type": "InsertBefore", 
          "seed": "if (n4.value < n1.value) {\n  small.value=n4.value;\n}"
        }, 
        {
          "path": "src/main/java/introclassJava/smallest_3b2376ab_007.java", 
          "line": 76, 
          "faulty": "small.value=n4.value;", 
          "type": "Replace", 
          "seed": "if (n4.value < n1.value) {\n  small.value=n4.value;\n}"
        }, 
        {
          "path": "src/main/java/introclassJava/smallest_3b2376ab_007.java", 
          "line": 82, 
          "faulty": ";", 
          "type": "InsertBefore", 
          "seed": "small.value=n3.value;"
        }
      ]
    }, 
    {
      "edits": [
        {
          "path": "src/main/java/introclassJava/smallest_3b2376ab_007.java", 
          "line": 75, 
          "faulty": "if (n4.value < n3.value) {\n  small.value=n4.value;\n}\n else if (n4.value < n1.value) {\n  small.value=n4.value;\n}", 
          "type": "Delete", 
          "seed": "output+=(String.format(\"%d is the smallest\\n\",small.value));"
        }, 
        {
          "path": "src/main/java/introclassJava/smallest_3b2376ab_007.java", 
          "line": 76, 
          "faulty": "small.value=n4.value;", 
          "type": "Delete", 
          "seed": "small.value=n3.value;"
        }, 
        {
          "path": "src/main/java/introclassJava/smallest_3b2376ab_007.java", 
          "line": 80, 
          "faulty": "output+=(String.format(\"%d is the smallest\\n\",small.value));", 
          "type": "InsertBefore", 
          "seed": "if (n4.value < n1.value) {\n  small.value=n4.value;\n}"
        }
      ]
    }, 
    {
      "edits": [
        {
          "path": "src/main/java/introclassJava/smallest_3b2376ab_007.java", 
          "line": 76, 
          "faulty": "small.value=n4.value;", 
          "type": "Replace", 
          "seed": "if (n4.value < n1.value) {\n  small.value=n4.value;\n}"
        }, 
        {
          "path": "src/main/java/introclassJava/smallest_3b2376ab_007.java", 
          "line": 82, 
          "faulty": "return;", 
          "type": "Delete", 
          "seed": "output+=(String.format(\"Please enter 4 numbers separated by spaces > \"));"
        }, 
        {
          "path": "src/main/java/introclassJava/smallest_3b2376ab_007.java", 
          "line": 82, 
          "faulty": ";", 
          "type": "InsertBefore", 
          "seed": "small.value=n1.value;"
        }
      ]
    }, 
    {
      "edits": [
        {
          "path": "src/main/java/introclassJava/smallest_3b2376ab_007.java", 
          "line": 76, 
          "faulty": "small.value=n4.value;", 
          "type": "Replace", 
          "seed": "if (n4.value < n1.value) {\n  small.value=n4.value;\n}"
        }, 
        {
          "path": "src/main/java/introclassJava/smallest_3b2376ab_007.java", 
          "line": 82, 
          "faulty": ";", 
          "type": "Replace", 
          "seed": "small.value=n1.value;"
        }
      ]
    }, 
    {
      "edits": [
        {
          "path": "src/main/java/introclassJava/smallest_3b2376ab_007.java", 
          "line": 62, 
          "faulty": "output+=(String.format(\"Please enter 4 numbers separated by spaces > \"));", 
          "type": "InsertBefore", 
          "seed": "small.value=n4.value;"
        }, 
        {
          "path": "src/main/java/introclassJava/smallest_3b2376ab_007.java", 
          "line": 76, 
          "faulty": "small.value=n4.value;", 
          "type": "Replace", 
          "seed": "if (n4.value < n1.value) {\n  small.value=n4.value;\n}"
        }
      ]
    }, 
    {
      "edits": [
        {
          "path": "src/main/java/introclassJava/smallest_3b2376ab_007.java", 
          "line": 62, 
          "faulty": "output+=(String.format(\"Please enter 4 numbers separated by spaces > \"));", 
          "type": "InsertBefore", 
          "seed": "if (n4.value < n3.value) {\n  small.value=n4.value;\n}\n else if (n4.value < n1.value) {\n  small.value=n4.value;\n}"
        }, 
        {
          "path": "src/main/java/introclassJava/smallest_3b2376ab_007.java", 
          "line": 76, 
          "faulty": "small.value=n4.value;", 
          "type": "Replace", 
          "seed": "if (n4.value < n1.value) {\n  small.value=n4.value;\n}"
        }, 
        {
          "path": "src/main/java/introclassJava/smallest_3b2376ab_007.java", 
          "line": 82, 
          "faulty": "return;", 
          "type": "Delete", 
          "seed": "small.value=n3.value;"
        }
      ]
    }, 
    {
      "edits": [
        {
          "path": "src/main/java/introclassJava/smallest_3b2376ab_007.java", 
          "line": 65, 
          "faulty": "n2.value=scanner.nextInt();", 
          "type": "InsertBefore", 
          "seed": "if (n4.value < n1.value) {\n  small.value=n4.value;\n}"
        }, 
        {
          "path": "src/main/java/introclassJava/smallest_3b2376ab_007.java", 
          "line": 76, 
          "faulty": "small.value=n4.value;", 
          "type": "Replace", 
          "seed": "if (n4.value < n1.value) {\n  small.value=n4.value;\n}"
        }
      ]
    }, 
    {
      "edits": [
        {
          "path": "src/main/java/introclassJava/smallest_3b2376ab_007.java", 
          "line": 62, 
          "faulty": "output+=(String.format(\"Please enter 4 numbers separated by spaces > \"));", 
          "type": "InsertBefore", 
          "seed": "small.value=n2.value;"
        }, 
        {
          "path": "src/main/java/introclassJava/smallest_3b2376ab_007.java", 
          "line": 76, 
          "faulty": "small.value=n4.value;", 
          "type": "Replace", 
          "seed": "if (n4.value < n1.value) {\n  small.value=n4.value;\n}"
        }, 
        {
          "path": "src/main/java/introclassJava/smallest_3b2376ab_007.java", 
          "line": 82, 
          "faulty": ";", 
          "type": "InsertBefore", 
          "seed": "output+=(String.format(\"Please enter 4 numbers separated by spaces > \"));"
        }
      ]
    }, 
    {
      "edits": [
        {
          "path": "src/main/java/introclassJava/smallest_3b2376ab_007.java", 
          "line": 62, 
          "faulty": "output+=(String.format(\"Please enter 4 numbers separated by spaces > \"));", 
          "type": "InsertBefore", 
          "seed": "if (n3.value < n2.value) {\n  small.value=n3.value;\n}"
        }, 
        {
          "path": "src/main/java/introclassJava/smallest_3b2376ab_007.java", 
          "line": 66, 
          "faulty": "n3.value=scanner.nextInt();", 
          "type": "InsertBefore", 
          "seed": "if (n3.value < n2.value) {\n  small.value=n3.value;\n}"
        }, 
        {
          "path": "src/main/java/introclassJava/smallest_3b2376ab_007.java", 
          "line": 76, 
          "faulty": "small.value=n4.value;", 
          "type": "Replace", 
          "seed": "if (n4.value < n1.value) {\n  small.value=n4.value;\n}"
        }, 
        {
          "path": "src/main/java/introclassJava/smallest_3b2376ab_007.java", 
          "line": 82, 
          "faulty": ";", 
          "type": "InsertBefore", 
          "seed": "if (n4.value < n1.value) {\n  small.value=n4.value;\n}"
        }
      ]
    }, 
    {
      "edits": [
        {
          "path": "src/main/java/introclassJava/smallest_3b2376ab_007.java", 
          "line": 72, 
          "faulty": "if (n3.value < n2.value) {\n  small.value=n3.value;\n}", 
          "type": "InsertBefore", 
          "seed": ";"
        }, 
        {
          "path": "src/main/java/introclassJava/smallest_3b2376ab_007.java", 
          "line": 76, 
          "faulty": "small.value=n4.value;", 
          "type": "Replace", 
          "seed": "if (n4.value < n1.value) {\n  small.value=n4.value;\n}"
        }
      ]
    }, 
    {
      "edits": [
        {
          "path": "src/main/java/introclassJava/smallest_3b2376ab_007.java", 
          "line": 76, 
          "faulty": "small.value=n4.value;", 
          "type": "Replace", 
          "seed": "if (n4.value < n1.value) {\n  small.value=n4.value;\n}"
        }, 
        {
          "path": "src/main/java/introclassJava/smallest_3b2376ab_007.java", 
          "line": 82, 
          "faulty": ";", 
          "type": "InsertBefore", 
          "seed": "if (n4.value < n1.value) {\n  small.value=n4.value;\n}"
        }
      ]
    }, 
    {
      "edits": [
        {
          "path": "src/main/java/introclassJava/smallest_3b2376ab_007.java", 
          "line": 67, 
          "faulty": "n4.value=scanner.nextInt();", 
          "type": "InsertBefore", 
          "seed": "small.value=n2.value;"
        }, 
        {
          "path": "src/main/java/introclassJava/smallest_3b2376ab_007.java", 
          "line": 76, 
          "faulty": "small.value=n4.value;", 
          "type": "Replace", 
          "seed": "if (n4.value < n1.value) {\n  small.value=n4.value;\n}"
        }, 
        {
          "path": "src/main/java/introclassJava/smallest_3b2376ab_007.java", 
          "line": 82, 
          "faulty": ";", 
          "type": "InsertBefore", 
          "seed": "small.value=n3.value;"
        }
      ]
    }, 
    {
      "edits": [
        {
          "path": "src/main/java/introclassJava/smallest_3b2376ab_007.java", 
          "line": 76, 
          "faulty": "small.value=n4.value;", 
          "type": "Replace", 
          "seed": "if (n4.value < n1.value) {\n  small.value=n4.value;\n}"
        }, 
        {
          "path": "src/main/java/introclassJava/smallest_3b2376ab_007.java", 
          "line": 82, 
          "faulty": ";", 
          "type": "Replace", 
          "seed": "if (n4.value < n1.value) {\n  small.value=n4.value;\n}"
        }
      ]
    }, 
    {
      "edits": [
        {
          "path": "src/main/java/introclassJava/smallest_3b2376ab_007.java", 
          "line": 65, 
          "faulty": "n2.value=scanner.nextInt();", 
          "type": "InsertBefore", 
          "seed": "if (n4.value < n3.value) {\n  small.value=n4.value;\n}\n else if (n4.value < n1.value) {\n  small.value=n4.value;\n}"
        }, 
        {
          "path": "src/main/java/introclassJava/smallest_3b2376ab_007.java", 
          "line": 76, 
          "faulty": "small.value=n4.value;", 
          "type": "Replace", 
          "seed": "if (n4.value < n1.value) {\n  small.value=n4.value;\n}"
        }
      ]
    }, 
    {
      "edits": [
        {
          "path": "src/main/java/introclassJava/smallest_3b2376ab_007.java", 
          "line": 76, 
          "faulty": "small.value=n4.value;", 
          "type": "Replace", 
          "seed": "if (n4.value < n1.value) {\n  small.value=n4.value;\n}"
        }, 
        {
          "path": "src/main/java/introclassJava/smallest_3b2376ab_007.java", 
          "line": 80, 
          "faulty": "output+=(String.format(\"%d is the smallest\\n\",small.value));", 
          "type": "InsertBefore", 
          "seed": ";"
        }
      ]
    }, 
    {
      "edits": [
        {
          "path": "src/main/java/introclassJava/smallest_3b2376ab_007.java", 
          "line": 76, 
          "faulty": "small.value=n4.value;", 
          "type": "Replace", 
          "seed": "if (n4.value < n1.value) {\n  small.value=n4.value;\n}"
        }
      ]
    }, 
    {
      "edits": [
        {
          "path": "src/main/java/introclassJava/smallest_3b2376ab_007.java", 
          "line": 65, 
          "faulty": "n2.value=scanner.nextInt();", 
          "type": "InsertBefore", 
          "seed": "small.value=n3.value;"
        }, 
        {
          "path": "src/main/java/introclassJava/smallest_3b2376ab_007.java", 
          "line": 76, 
          "faulty": "small.value=n4.value;", 
          "type": "Replace", 
          "seed": "if (n4.value < n1.value) {\n  small.value=n4.value;\n}"
        }
      ]
    }, 
    {
      "edits": [
        {
          "path": "src/main/java/introclassJava/smallest_3b2376ab_007.java", 
          "line": 64, 
          "faulty": "n1.value=scanner.nextInt();", 
          "type": "InsertBefore", 
          "seed": "small.value=n3.value;"
        }, 
        {
          "path": "src/main/java/introclassJava/smallest_3b2376ab_007.java", 
          "line": 76, 
          "faulty": "small.value=n4.value;", 
          "type": "Replace", 
          "seed": "if (n4.value < n1.value) {\n  small.value=n4.value;\n}"
        }
      ]
    }, 
    {
      "edits": [
        {
          "path": "src/main/java/introclassJava/smallest_3b2376ab_007.java", 
          "line": 76, 
          "faulty": "small.value=n4.value;", 
          "type": "Replace", 
          "seed": "if (n4.value < n1.value) {\n  small.value=n4.value;\n}"
        }, 
        {
          "path": "src/main/java/introclassJava/smallest_3b2376ab_007.java", 
          "line": 82, 
          "faulty": "return;", 
          "type": "InsertBefore", 
          "seed": "small.value=n4.value;"
        }
      ]
    }, 
    {
      "edits": [
        {
          "path": "src/main/java/introclassJava/smallest_3b2376ab_007.java", 
          "line": 66, 
          "faulty": "n3.value=scanner.nextInt();", 
          "type": "InsertBefore", 
          "seed": "small.value=n1.value;"
        }, 
        {
          "path": "src/main/java/introclassJava/smallest_3b2376ab_007.java", 
          "line": 76, 
          "faulty": "small.value=n4.value;", 
          "type": "Replace", 
          "seed": "if (n4.value < n1.value) {\n  small.value=n4.value;\n}"
        }, 
        {
          "path": "src/main/java/introclassJava/smallest_3b2376ab_007.java", 
          "line": 80, 
          "faulty": "output+=(String.format(\"%d is the smallest\\n\",small.value));", 
          "type": "InsertBefore", 
          "seed": "if (n4.value < n1.value) {\n  small.value=n4.value;\n}"
        }
      ]
    }, 
    {
      "edits": [
        {
          "path": "src/main/java/introclassJava/smallest_3b2376ab_007.java", 
          "line": 62, 
          "faulty": "output+=(String.format(\"Please enter 4 numbers separated by spaces > \"));", 
          "type": "InsertBefore", 
          "seed": "small.value=n3.value;"
        }, 
        {
          "path": "src/main/java/introclassJava/smallest_3b2376ab_007.java", 
          "line": 76, 
          "faulty": "small.value=n4.value;", 
          "type": "Replace", 
          "seed": "if (n4.value < n1.value) {\n  small.value=n4.value;\n}"
        }
      ]
    }, 
    {
      "edits": [
        {
          "path": "src/main/java/introclassJava/smallest_3b2376ab_007.java", 
          "line": 62, 
          "faulty": "output+=(String.format(\"Please enter 4 numbers separated by spaces > \"));", 
          "type": "InsertBefore", 
          "seed": "small.value=n1.value;"
        }, 
        {
          "path": "src/main/java/introclassJava/smallest_3b2376ab_007.java", 
          "line": 76, 
          "faulty": "small.value=n4.value;", 
          "type": "Replace", 
          "seed": "if (n4.value < n1.value) {\n  small.value=n4.value;\n}"
        }
      ]
    }, 
    {
      "edits": [
        {
          "path": "src/main/java/introclassJava/smallest_3b2376ab_007.java", 
          "line": 76, 
          "faulty": "small.value=n4.value;", 
          "type": "Replace", 
          "seed": "if (n4.value < n1.value) {\n  small.value=n4.value;\n}"
        }, 
        {
          "path": "src/main/java/introclassJava/smallest_3b2376ab_007.java", 
          "line": 82, 
          "faulty": "return;", 
          "type": "Replace", 
          "seed": "small.value=n2.value;"
        }
      ]
    }, 
    {
      "edits": [
        {
          "path": "src/main/java/introclassJava/smallest_3b2376ab_007.java", 
          "line": 62, 
          "faulty": "output+=(String.format(\"Please enter 4 numbers separated by spaces > \"));", 
          "type": "InsertBefore", 
          "seed": "if (n4.value < n3.value) {\n  small.value=n4.value;\n}\n else if (n4.value < n1.value) {\n  small.value=n4.value;\n}"
        }, 
        {
          "path": "src/main/java/introclassJava/smallest_3b2376ab_007.java", 
          "line": 76, 
          "faulty": "small.value=n4.value;", 
          "type": "Replace", 
          "seed": "if (n4.value < n1.value) {\n  small.value=n4.value;\n}"
        }
      ]
    }, 
    {
      "edits": [
        {
          "path": "src/main/java/introclassJava/smallest_3b2376ab_007.java", 
          "line": 60, 
          "faulty": "IntObj n1=new IntObj(), n2=new IntObj(), n3=new IntObj(), n4=new IntObj(), small=new IntObj();", 
          "type": "InsertBefore", 
          "seed": ";"
        }, 
        {
          "path": "src/main/java/introclassJava/smallest_3b2376ab_007.java", 
          "line": 76, 
          "faulty": "small.value=n4.value;", 
          "type": "Replace", 
          "seed": "if (n4.value < n1.value) {\n  small.value=n4.value;\n}"
        }
      ]
    }, 
    {
      "edits": [
        {
          "path": "src/main/java/introclassJava/smallest_3b2376ab_007.java", 
          "line": 62, 
          "faulty": "output+=(String.format(\"Please enter 4 numbers separated by spaces > \"));", 
          "type": "InsertBefore", 
          "seed": "small.value=n2.value;"
        }, 
        {
          "path": "src/main/java/introclassJava/smallest_3b2376ab_007.java", 
          "line": 76, 
          "faulty": "small.value=n4.value;", 
          "type": "Replace", 
          "seed": "if (n4.value < n1.value) {\n  small.value=n4.value;\n}"
        }
      ]
    }, 
    {
      "edits": [
        {
          "path": "src/main/java/introclassJava/smallest_3b2376ab_007.java", 
          "line": 66, 
          "faulty": "n3.value=scanner.nextInt();", 
          "type": "InsertBefore", 
          "seed": "if (n2.value < n1.value) {\n  small.value=n2.value;\n}"
        }, 
        {
          "path": "src/main/java/introclassJava/smallest_3b2376ab_007.java", 
          "line": 76, 
          "faulty": "small.value=n4.value;", 
          "type": "Replace", 
          "seed": "if (n4.value < n1.value) {\n  small.value=n4.value;\n}"
        }
      ]
    }, 
    {
      "edits": [
        {
          "path": "src/main/java/introclassJava/smallest_3b2376ab_007.java", 
          "line": 76, 
          "faulty": "small.value=n4.value;", 
          "type": "Replace", 
          "seed": "if (n4.value < n1.value) {\n  small.value=n4.value;\n}"
        }, 
        {
          "path": "src/main/java/introclassJava/smallest_3b2376ab_007.java", 
          "line": 82, 
          "faulty": "return;", 
          "type": "Replace", 
          "seed": "small.value=n4.value;"
        }, 
        {
          "path": "src/main/java/introclassJava/smallest_3b2376ab_007.java", 
          "line": 82, 
          "faulty": ";", 
          "type": "InsertBefore", 
          "seed": "small.value=n3.value;"
        }
      ]
    }, 
    {
      "edits": [
        {
          "path": "src/main/java/introclassJava/smallest_3b2376ab_007.java", 
          "line": 62, 
          "faulty": "output+=(String.format(\"Please enter 4 numbers separated by spaces > \"));", 
          "type": "InsertBefore", 
          "seed": "if (n4.value < n3.value) {\n  small.value=n4.value;\n}\n else if (n4.value < n1.value) {\n  small.value=n4.value;\n}"
        }, 
        {
          "path": "src/main/java/introclassJava/smallest_3b2376ab_007.java", 
          "line": 64, 
          "faulty": "n1.value=scanner.nextInt();", 
          "type": "InsertBefore", 
          "seed": ";"
        }, 
        {
          "path": "src/main/java/introclassJava/smallest_3b2376ab_007.java", 
          "line": 76, 
          "faulty": "small.value=n4.value;", 
          "type": "Replace", 
          "seed": "if (n4.value < n1.value) {\n  small.value=n4.value;\n}"
        }
      ]
    }, 
    {
      "edits": [
        {
          "path": "src/main/java/introclassJava/smallest_3b2376ab_007.java", 
          "line": 64, 
          "faulty": "n1.value=scanner.nextInt();", 
          "type": "InsertBefore", 
          "seed": "small.value=n3.value;"
        }, 
        {
          "path": "src/main/java/introclassJava/smallest_3b2376ab_007.java", 
          "line": 76, 
          "faulty": "small.value=n4.value;", 
          "type": "Replace", 
          "seed": "if (n4.value < n1.value) {\n  small.value=n4.value;\n}"
        }, 
        {
          "path": "src/main/java/introclassJava/smallest_3b2376ab_007.java", 
          "line": 82, 
          "faulty": ";", 
          "type": "Delete", 
          "seed": "small.value=n2.value;"
        }
      ]
    }, 
    {
      "edits": [
        {
          "path": "src/main/java/introclassJava/smallest_3b2376ab_007.java", 
          "line": 66, 
          "faulty": "n3.value=scanner.nextInt();", 
          "type": "InsertBefore", 
          "seed": "if (n3.value < n2.value) {\n  small.value=n3.value;\n}"
        }, 
        {
          "path": "src/main/java/introclassJava/smallest_3b2376ab_007.java", 
          "line": 76, 
          "faulty": "small.value=n4.value;", 
          "type": "Replace", 
          "seed": "if (n4.value < n1.value) {\n  small.value=n4.value;\n}"
        }
      ]
    }, 
    {
      "edits": [
        {
          "path": "src/main/java/introclassJava/smallest_3b2376ab_007.java", 
          "line": 62, 
          "faulty": "output+=(String.format(\"Please enter 4 numbers separated by spaces > \"));", 
          "type": "InsertBefore", 
          "seed": "small.value=n4.value;"
        }, 
        {
          "path": "src/main/java/introclassJava/smallest_3b2376ab_007.java", 
          "line": 76, 
          "faulty": "small.value=n4.value;", 
          "type": "Replace", 
          "seed": "if (n4.value < n1.value) {\n  small.value=n4.value;\n}"
        }, 
        {
          "path": "src/main/java/introclassJava/smallest_3b2376ab_007.java", 
          "line": 82, 
          "faulty": ";", 
          "type": "InsertBefore", 
          "seed": "small.value=n3.value;"
        }
      ]
    }, 
    {
      "edits": [
        {
          "path": "src/main/java/introclassJava/smallest_3b2376ab_007.java", 
          "line": 76, 
          "faulty": "small.value=n4.value;", 
          "type": "Replace", 
          "seed": "if (n4.value < n1.value) {\n  small.value=n4.value;\n}"
        }, 
        {
          "path": "src/main/java/introclassJava/smallest_3b2376ab_007.java", 
          "line": 82, 
          "faulty": "return;", 
          "type": "Delete", 
          "seed": "output+=(String.format(\"Please enter 4 numbers separated by spaces > \"));"
        }
      ]
    }, 
    {
      "edits": [
        {
          "path": "src/main/java/introclassJava/smallest_3b2376ab_007.java", 
          "line": 76, 
          "faulty": "small.value=n4.value;", 
          "type": "Replace", 
          "seed": "if (n4.value < n1.value) {\n  small.value=n4.value;\n}"
        }, 
        {
          "path": "src/main/java/introclassJava/smallest_3b2376ab_007.java", 
          "line": 82, 
          "faulty": ";", 
          "type": "InsertBefore", 
          "seed": "output+=(String.format(\"%d is the smallest\\n\",small.value));"
        }
      ]
    }, 
    {
      "edits": [
        {
          "path": "src/main/java/introclassJava/smallest_3b2376ab_007.java", 
          "line": 75, 
          "faulty": "if (n4.value < n3.value) {\n  small.value=n4.value;\n}\n else if (n4.value < n1.value) {\n  small.value=n4.value;\n}", 
          "type": "Replace", 
          "seed": "if (n4.value < n1.value) {\n  small.value=n4.value;\n}"
        }, 
        {
          "path": "src/main/java/introclassJava/smallest_3b2376ab_007.java", 
          "line": 76, 
          "faulty": "small.value=n4.value;", 
          "type": "Replace", 
          "seed": "if (n4.value < n1.value) {\n  small.value=n4.value;\n}"
        }
      ]
    }, 
    {
      "edits": [
        {
          "path": "src/main/java/introclassJava/smallest_3b2376ab_007.java", 
          "line": 64, 
          "faulty": "n1.value=scanner.nextInt();", 
          "type": "InsertBefore", 
          "seed": ";"
        }, 
        {
          "path": "src/main/java/introclassJava/smallest_3b2376ab_007.java", 
          "line": 76, 
          "faulty": "small.value=n4.value;", 
          "type": "Replace", 
          "seed": "if (n4.value < n1.value) {\n  small.value=n4.value;\n}"
        }
      ]
    }, 
    {
      "edits": [
        {
          "path": "src/main/java/introclassJava/smallest_3b2376ab_007.java", 
          "line": 66, 
          "faulty": "n3.value=scanner.nextInt();", 
          "type": "InsertBefore", 
          "seed": ";"
        }, 
        {
          "path": "src/main/java/introclassJava/smallest_3b2376ab_007.java", 
          "line": 76, 
          "faulty": "small.value=n4.value;", 
          "type": "Replace", 
          "seed": "if (n4.value < n1.value) {\n  small.value=n4.value;\n}"
        }
      ]
    }, 
    {
      "edits": [
        {
          "path": "src/main/java/introclassJava/smallest_3b2376ab_007.java", 
          "line": 62, 
          "faulty": "output+=(String.format(\"Please enter 4 numbers separated by spaces > \"));", 
          "type": "InsertBefore", 
          "seed": "small.value=n3.value;"
        }, 
        {
          "path": "src/main/java/introclassJava/smallest_3b2376ab_007.java", 
          "line": 65, 
          "faulty": "n2.value=scanner.nextInt();", 
          "type": "InsertBefore", 
          "seed": "if (n4.value < n3.value) {\n  small.value=n4.value;\n}\n else if (n4.value < n1.value) {\n  small.value=n4.value;\n}"
        }, 
        {
          "path": "src/main/java/introclassJava/smallest_3b2376ab_007.java", 
          "line": 76, 
          "faulty": "small.value=n4.value;", 
          "type": "Replace", 
          "seed": "if (n4.value < n1.value) {\n  small.value=n4.value;\n}"
        }
      ]
    }, 
    {
      "edits": [
        {
          "path": "src/main/java/introclassJava/smallest_3b2376ab_007.java", 
          "line": 62, 
          "faulty": "output+=(String.format(\"Please enter 4 numbers separated by spaces > \"));", 
          "type": "InsertBefore", 
          "seed": "if (n3.value < n2.value) {\n  small.value=n3.value;\n}"
        }, 
        {
          "path": "src/main/java/introclassJava/smallest_3b2376ab_007.java", 
          "line": 68, 
          "faulty": "small.value=n1.value;", 
          "type": "InsertBefore", 
          "seed": "if (n4.value < n1.value) {\n  small.value=n4.value;\n}"
        }, 
        {
          "path": "src/main/java/introclassJava/smallest_3b2376ab_007.java", 
          "line": 72, 
          "faulty": "if (n3.value < n2.value) {\n  small.value=n3.value;\n}", 
          "type": "InsertBefore", 
          "seed": "if (n3.value < n2.value) {\n  small.value=n3.value;\n}"
        }, 
        {
          "path": "src/main/java/introclassJava/smallest_3b2376ab_007.java", 
          "line": 76, 
          "faulty": "small.value=n4.value;", 
          "type": "Replace", 
          "seed": "if (n4.value < n1.value) {\n  small.value=n4.value;\n}"
        }
      ]
    }, 
    {
      "edits": [
        {
          "path": "src/main/java/introclassJava/smallest_3b2376ab_007.java", 
          "line": 76, 
          "faulty": "small.value=n4.value;", 
          "type": "Replace", 
          "seed": "if (n4.value < n1.value) {\n  small.value=n4.value;\n}"
        }, 
        {
          "path": "src/main/java/introclassJava/smallest_3b2376ab_007.java", 
          "line": 82, 
          "faulty": ";", 
          "type": "Delete", 
          "seed": "n3.value=scanner.nextInt();"
        }
      ]
    }, 
    {
      "edits": [
        {
          "path": "src/main/java/introclassJava/smallest_3b2376ab_007.java", 
          "line": 76, 
          "faulty": "small.value=n4.value;", 
          "type": "Replace", 
          "seed": "if (n4.value < n1.value) {\n  small.value=n4.value;\n}"
        }, 
        {
          "path": "src/main/java/introclassJava/smallest_3b2376ab_007.java", 
          "line": 82, 
          "faulty": "return;", 
          "type": "Delete", 
          "seed": "output+=(String.format(\"Please enter 4 numbers separated by spaces > \"));"
        }, 
        {
          "path": "src/main/java/introclassJava/smallest_3b2376ab_007.java", 
          "line": 82, 
          "faulty": ";", 
          "type": "Delete", 
          "seed": "n3.value=scanner.nextInt();"
        }
      ]
    }, 
    {
      "edits": [
        {
          "path": "src/main/java/introclassJava/smallest_3b2376ab_007.java", 
          "line": 67, 
          "faulty": "n4.value=scanner.nextInt();", 
          "type": "InsertBefore", 
          "seed": "small.value=n2.value;"
        }, 
        {
          "path": "src/main/java/introclassJava/smallest_3b2376ab_007.java", 
          "line": 76, 
          "faulty": "small.value=n4.value;", 
          "type": "Replace", 
          "seed": "if (n4.value < n1.value) {\n  small.value=n4.value;\n}"
        }, 
        {
          "path": "src/main/java/introclassJava/smallest_3b2376ab_007.java", 
          "line": 82, 
          "faulty": ";", 
          "type": "InsertBefore", 
          "seed": "output+=(String.format(\"Please enter 4 numbers separated by spaces > \"));"
        }
      ]
    }, 
    {
      "edits": [
        {
          "path": "src/main/java/introclassJava/smallest_3b2376ab_007.java", 
          "line": 67, 
          "faulty": "n4.value=scanner.nextInt();", 
          "type": "InsertBefore", 
          "seed": ";"
        }, 
        {
          "path": "src/main/java/introclassJava/smallest_3b2376ab_007.java", 
          "line": 76, 
          "faulty": "small.value=n4.value;", 
          "type": "Replace", 
          "seed": "if (n4.value < n1.value) {\n  small.value=n4.value;\n}"
        }
      ]
    }, 
    {
      "edits": [
        {
          "path": "src/main/java/introclassJava/smallest_3b2376ab_007.java", 
          "line": 62, 
          "faulty": "output+=(String.format(\"Please enter 4 numbers separated by spaces > \"));", 
          "type": "InsertBefore", 
          "seed": "if (n4.value < n3.value) {\n  small.value=n4.value;\n}\n else if (n4.value < n1.value) {\n  small.value=n4.value;\n}"
        }, 
        {
          "path": "src/main/java/introclassJava/smallest_3b2376ab_007.java", 
          "line": 76, 
          "faulty": "small.value=n4.value;", 
          "type": "Replace", 
          "seed": "if (n4.value < n1.value) {\n  small.value=n4.value;\n}"
        }, 
        {
          "path": "src/main/java/introclassJava/smallest_3b2376ab_007.java", 
          "line": 82, 
          "faulty": ";", 
          "type": "InsertBefore", 
          "seed": "small.value=n3.value;"
        }
      ]
    }, 
    {
      "edits": [
        {
          "path": "src/main/java/introclassJava/smallest_3b2376ab_007.java", 
          "line": 76, 
          "faulty": "small.value=n4.value;", 
          "type": "Replace", 
          "seed": "if (n4.value < n1.value) {\n  small.value=n4.value;\n}"
        }, 
        {
          "path": "src/main/java/introclassJava/smallest_3b2376ab_007.java", 
          "line": 82, 
          "faulty": ";", 
          "type": "InsertBefore", 
          "seed": "small.value=n2.value;"
        }
      ]
    }, 
    {
      "edits": [
        {
          "path": "src/main/java/introclassJava/smallest_3b2376ab_007.java", 
          "line": 76, 
          "faulty": "small.value=n4.value;", 
          "type": "Replace", 
          "seed": "if (n4.value < n1.value) {\n  small.value=n4.value;\n}"
        }, 
        {
          "path": "src/main/java/introclassJava/smallest_3b2376ab_007.java", 
          "line": 82, 
          "faulty": ";", 
          "type": "InsertBefore", 
          "seed": "n3.value=scanner.nextInt();"
        }
      ]
    }, 
    {
      "edits": [
        {
          "path": "src/main/java/introclassJava/smallest_3b2376ab_007.java", 
          "line": 76, 
          "faulty": "small.value=n4.value;", 
          "type": "Replace", 
          "seed": "if (n4.value < n1.value) {\n  small.value=n4.value;\n}"
        }, 
        {
          "path": "src/main/java/introclassJava/smallest_3b2376ab_007.java", 
          "line": 82, 
          "faulty": ";", 
          "type": "InsertBefore", 
          "seed": "small.value=n1.value;"
        }
      ]
    }, 
    {
      "edits": [
        {
          "path": "src/main/java/introclassJava/smallest_3b2376ab_007.java", 
          "line": 66, 
          "faulty": "n3.value=scanner.nextInt();", 
          "type": "InsertBefore", 
          "seed": "small.value=n4.value;"
        }, 
        {
          "path": "src/main/java/introclassJava/smallest_3b2376ab_007.java", 
          "line": 76, 
          "faulty": "small.value=n4.value;", 
          "type": "Replace", 
          "seed": "if (n4.value < n1.value) {\n  small.value=n4.value;\n}"
        }
      ]
    }
  ]
}